README.txt
TODO.txt
freeze.sh
freeze_reload.sh
setup.py
docs/HISTORY.txt
mr/__init__.py
mr.freeze.egg-info/PKG-INFO
mr.freeze.egg-info/SOURCES.txt
mr.freeze.egg-info/dependency_links.txt
mr.freeze.egg-info/namespace_packages.txt
mr.freeze.egg-info/not-zip-safe
mr.freeze.egg-info/requires.txt
mr.freeze.egg-info/top_level.txt
mr/freeze/__init__.py
mr/freeze/configure.zcml
mr/freeze/freeze.py
mr/freeze/patches.py