Metadata-Version: 1.0
Name: mr.freeze
Version: 1.0a2
Summary: Trigger a pdb in a running zope via a USR1 signal
Home-page: http://en.wikipedia.org/wiki/Mr._Freeze
Author: David Glick
Author-email: davidglick@onenw.org
License: BSD
Keywords: zope debugging pdb
Platform: UNKNOWN
Classifier: Development Status :: 3 - Alpha
Classifier: Intended Audience :: Developers
Classifier: Programming Language :: Python
Classifier: Framework :: Zope2
Classifier: Topic :: Software Development :: Libraries :: Python Modules
